setup.py
ggthrift.egg-info/PKG-INFO
ggthrift.egg-info/SOURCES.txt
ggthrift.egg-info/dependency_links.txt
ggthrift.egg-info/entry_points.txt
ggthrift.egg-info/not-zip-safe
ggthrift.egg-info/requires.txt
ggthrift.egg-info/top_level.txt
gunicorn_thrift/__init__.py
gunicorn_thrift/thriftlogging.py
gunicorn_thrift/app/__init__.py
gunicorn_thrift/app/thriftapp.py
gunicorn_thrift/thrift/__init__.py
gunicorn_thrift/thrift/protocol.py
gunicorn_thrift/workers/__init__.py
gunicorn_thrift/workers/gthriftgevent.py