Metadata-Version: 1.0
Name: ggthrift
Version: 19.1.2
Summary: python thrift server plugin for gunicorn.
Home-page: http://github.com/wmttom/gunicorn_thrift
Author: wmttom
Author-email: wmttom@gmail.com
License: MIT
Platform: UNKNOWN
